gemini_data_extractor/__init__.py
gemini_data_extractor/api_caller.py
gemini_data_extractor-0.1.2.dist-info/METADATA
gemini_data_extractor-0.1.2.dist-info/WHEEL
gemini_data_extractor-0.1.2.dist-info/entry_points.txt
gemini_data_extractor-0.1.2.dist-info/licenses/LICENSE
gemini_data_extractor-0.1.2.dist-info/RECORD
