Metadata-Version: 2.4
Name: gemini-data-extractor
Version: 0.1.2
Summary: A simple tool to extract data from PDFs and images using Google's gemini-2.0-flash-001 model.
Author-email: Domenico Delle Side <nico@delleside.org>
License-File: LICENSE
Requires-Python: >=3.12
Requires-Dist: google-genai>=1.3.0
